<?xml version="1.0" encoding="UTF-8"?>
<mxGraphModel dx="966" dy="486" grid="1" gridSize="10" guides="1" tooltips="1" connect="1" arrows="1" fold="1" page="1" pageScale="1" pageWidth="850" pageHeight="1100" background="#ffffff" math="0" shadow="0"><root><mxCell id="0"/><mxCell id="1" parent="0"/><mxCell id="2" value="User" style="swimlane;html=1;fontStyle=0;childLayout=stackLayout;horizontal=1;startSize=26;fillColor=#e0e0e0;horizontalStack=0;resizeParent=1;resizeLast=0;collapsible=1;marginBottom=0;swimlaneFillColor=#ffffff;align=center;" parent="1" vertex="1"><mxGeometry x="70" y="82" width="160" height="181" as="geometry"/></mxCell><mxCell id="3" value="Unique Email" style="text;html=1;strokeColor=none;fillColor=none;spacingLeft=4;spacingRight=4;whiteSpace=wrap;overflow=hidden;rotatable=0;points=[[0,0.5],[1,0.5]];portConstraint=eastwest;" parent="2" vertex="1"><mxGeometry y="26" width="160" height="24" as="geometry"/></mxCell><mxCell id="10" value="Problems" style="swimlane;html=1;fontStyle=0;childLayout=stackLayout;horizontal=1;startSize=26;fillColor=#e0e0e0;horizontalStack=0;resizeParent=1;resizeLast=0;collapsible=1;marginBottom=0;swimlaneFillColor=#ffffff;align=center;" parent="1" vertex="1"><mxGeometry x="580" y="89" width="160" height="188" as="geometry"/></mxCell><mxCell id="11" value="problem description" style="text;html=1;strokeColor=none;fillColor=none;spacingLeft=4;spacingRight=4;whiteSpace=wrap;overflow=hidden;rotatable=0;points=[[0,0.5],[1,0.5]];portConstraint=eastwest;" parent="10" vertex="1"><mxGeometry y="26" width="160" height="26" as="geometry"/></mxCell><mxCell id="12" value="Solutions" style="text;html=1;strokeColor=none;fillColor=none;spacingLeft=4;spacingRight=4;whiteSpace=wrap;overflow=hidden;rotatable=0;points=[[0,0.5],[1,0.5]];portConstraint=eastwest;" parent="10" vertex="1"><mxGeometry y="52" width="160" height="26" as="geometry"/></mxCell><mxCell id="51" value="Difficultly Level" style="text;html=1;strokeColor=none;fillColor=none;spacingLeft=4;spacingRight=4;whiteSpace=wrap;overflow=hidden;rotatable=0;points=[[0,0.5],[1,0.5]];portConstraint=eastwest;" parent="10" vertex="1"><mxGeometry y="78" width="160" height="32" as="geometry"/></mxCell><mxCell id="70c1fabb3b7ea038-53" value="Organization or null(public)" style="text;html=1;strokeColor=none;fillColor=none;spacingLeft=4;spacingRight=4;whiteSpace=wrap;overflow=hidden;rotatable=0;points=[[0,0.5],[1,0.5]];portConstraint=eastwest;" parent="10" vertex="1"><mxGeometry y="110" width="160" height="23" as="geometry"/></mxCell><mxCell id="302e782255bbe1b2-72" value="Stats" style="text;html=1;strokeColor=none;fillColor=none;spacingLeft=4;spacingRight=4;whiteSpace=wrap;overflow=hidden;rotatable=0;points=[[0,0.5],[1,0.5]];portConstraint=eastwest;" parent="10" vertex="1"><mxGeometry y="133" width="160" height="23" as="geometry"/></mxCell><mxCell id="46" value="Username" style="text;html=1;strokeColor=none;fillColor=none;spacingLeft=4;spacingRight=4;whiteSpace=wrap;overflow=hidden;rotatable=0;points=[[0,0.5],[1,0.5]];portConstraint=eastwest;" parent="1" vertex="1"><mxGeometry x="80" y="138" width="160" height="26" as="geometry"/></mxCell><mxCell id="47" value="Interview" style="swimlane;html=1;fontStyle=0;childLayout=stackLayout;horizontal=1;startSize=26;fillColor=#e0e0e0;horizontalStack=0;resizeParent=1;resizeLast=0;collapsible=1;marginBottom=0;swimlaneFillColor=#ffffff;align=center;" parent="1" vertex="1"><mxGeometry x="150" y="300" width="160" height="222" as="geometry"/></mxCell><mxCell id="49" value="Candidate" style="text;html=1;strokeColor=none;fillColor=none;spacingLeft=4;spacingRight=4;whiteSpace=wrap;overflow=hidden;rotatable=0;points=[[0,0.5],[1,0.5]];portConstraint=eastwest;" parent="47" vertex="1"><mxGeometry y="26" width="160" height="26" as="geometry"/></mxCell><mxCell id="50" value="Interviewer" style="text;html=1;strokeColor=none;fillColor=none;spacingLeft=4;spacingRight=4;whiteSpace=wrap;overflow=hidden;rotatable=0;points=[[0,0.5],[1,0.5]];portConstraint=eastwest;" parent="47" vertex="1"><mxGeometry y="52" width="160" height="26" as="geometry"/></mxCell><mxCell id="302e782255bbe1b2-75" value="date, time" style="text;html=1;strokeColor=none;fillColor=none;spacingLeft=4;spacingRight=4;whiteSpace=wrap;overflow=hidden;rotatable=0;points=[[0,0.5],[1,0.5]];portConstraint=eastwest;" parent="47" vertex="1"><mxGeometry y="78" width="160" height="26" as="geometry"/></mxCell><mxCell id="53" value="job type / position" style="text;html=1;strokeColor=none;fillColor=none;spacingLeft=4;spacingRight=4;whiteSpace=wrap;overflow=hidden;rotatable=0;points=[[0,0.5],[1,0.5]];portConstraint=eastwest;" parent="47" vertex="1"><mxGeometry y="104" width="160" height="26" as="geometry"/></mxCell><mxCell id="70c1fabb3b7ea038-54" value="status: planned, done" style="text;html=1;strokeColor=none;fillColor=none;spacingLeft=4;spacingRight=4;whiteSpace=wrap;overflow=hidden;rotatable=0;points=[[0,0.5],[1,0.5]];portConstraint=eastwest;" parent="47" vertex="1"><mxGeometry y="130" width="160" height="26" as="geometry"/></mxCell><mxCell id="70c1fabb3b7ea038-70" value="candidate rating/comments" style="text;html=1;strokeColor=none;fillColor=none;spacingLeft=4;spacingRight=4;whiteSpace=wrap;overflow=hidden;rotatable=0;points=[[0,0.5],[1,0.5]];portConstraint=eastwest;" parent="47" vertex="1"><mxGeometry y="156" width="160" height="26" as="geometry"/></mxCell><mxCell id="70c1fabb3b7ea038-66" value="problem list" style="text;html=1;strokeColor=none;fillColor=none;spacingLeft=4;spacingRight=4;whiteSpace=wrap;overflow=hidden;rotatable=0;points=[[0,0.5],[1,0.5]];portConstraint=eastwest;" parent="47" vertex="1"><mxGeometry y="182" width="160" height="26" as="geometry"/></mxCell><mxCell id="302e782255bbe1b2-66" value="password" style="text;html=1;strokeColor=none;fillColor=none;spacingLeft=4;spacingRight=4;whiteSpace=wrap;overflow=hidden;rotatable=0;points=[[0,0.5],[1,0.5]];portConstraint=eastwest;" parent="1" vertex="1"><mxGeometry x="80" y="159" width="160" height="26" as="geometry"/></mxCell><mxCell id="302e782255bbe1b2-67" style="edgeStyle=orthogonalEdgeStyle;rounded=0;html=1;exitX=0.5;exitY=1;entryX=0.5;entryY=1;jettySize=auto;orthogonalLoop=1;" parent="1" source="2" target="2" edge="1"><mxGeometry relative="1" as="geometry"/></mxCell><mxCell id="302e782255bbe1b2-68" value="role" style="text;html=1;strokeColor=none;fillColor=none;spacingLeft=4;spacingRight=4;whiteSpace=wrap;overflow=hidden;rotatable=0;points=[[0,0.5],[1,0.5]];portConstraint=eastwest;" parent="1" vertex="1"><mxGeometry x="82" y="180" width="160" height="26" as="geometry"/></mxCell><mxCell id="302e782255bbe1b2-73" value="" style="edgeStyle=elbowEdgeStyle;html=1;endArrow=ERmandOne;startArrow=ERmandOne;exitX=0;exitY=0.5;" parent="1" source="49" edge="1"><mxGeometry width="100" height="100" relative="1" as="geometry"><mxPoint x="384" y="360" as="sourcePoint"/><mxPoint x="70" y="210" as="targetPoint"/><Array as="points"><mxPoint x="20" y="290"/></Array></mxGeometry></mxCell><mxCell id="302e782255bbe1b2-85" value="" style="edgeStyle=elbowEdgeStyle;html=1;endArrow=ERmandOne;startArrow=ERmandOne;exitX=0;exitY=0.5;" parent="1" source="50" edge="1"><mxGeometry x="-250" y="270" width="100" height="100" as="geometry"><mxPoint x="490" y="380" as="sourcePoint"/><mxPoint x="70" y="240" as="targetPoint"/><Array as="points"><mxPoint x="40" y="320"/></Array></mxGeometry></mxCell><mxCell id="302e782255bbe1b2-87" value="Interview Problem List" style="swimlane;html=1;fontStyle=0;childLayout=stackLayout;horizontal=1;startSize=26;fillColor=#e0e0e0;horizontalStack=0;resizeParent=1;resizeLast=0;collapsible=1;marginBottom=0;swimlaneFillColor=#ffffff;align=center;" parent="1" vertex="1"><mxGeometry x="400" y="311" width="160" height="200" as="geometry"><mxRectangle x="630" y="255" width="80" height="26" as="alternateBounds"/></mxGeometry></mxCell><mxCell id="302e782255bbe1b2-88" value="problem ID" style="text;html=1;strokeColor=none;fillColor=none;spacingLeft=4;spacingRight=4;whiteSpace=wrap;overflow=hidden;rotatable=0;points=[[0,0.5],[1,0.5]];portConstraint=eastwest;" parent="302e782255bbe1b2-87" vertex="1"><mxGeometry y="26" width="160" height="26" as="geometry"/></mxCell><mxCell id="302e782255bbe1b2-89" value="Interview ID" style="text;html=1;strokeColor=none;fillColor=none;spacingLeft=4;spacingRight=4;whiteSpace=wrap;overflow=hidden;rotatable=0;points=[[0,0.5],[1,0.5]];portConstraint=eastwest;" parent="302e782255bbe1b2-87" vertex="1"><mxGeometry y="52" width="160" height="26" as="geometry"/></mxCell><mxCell id="302e782255bbe1b2-91" value="Interviewer Rating on Candidate performance" style="text;html=1;strokeColor=none;fillColor=none;spacingLeft=4;spacingRight=4;whiteSpace=wrap;overflow=hidden;rotatable=0;points=[[0,0.5],[1,0.5]];portConstraint=eastwest;" parent="302e782255bbe1b2-87" vertex="1"><mxGeometry y="78" width="160" height="32" as="geometry"/></mxCell><mxCell id="302e782255bbe1b2-90" value="Candidate Rating on problem (optional)" style="text;html=1;strokeColor=none;fillColor=none;spacingLeft=4;spacingRight=4;whiteSpace=wrap;overflow=hidden;rotatable=0;points=[[0,0.5],[1,0.5]];portConstraint=eastwest;" parent="302e782255bbe1b2-87" vertex="1"><mxGeometry y="110" width="160" height="32" as="geometry"/></mxCell><mxCell id="70c1fabb3b7ea038-69" value="problem status (planned, used, not used, reviewd)" style="text;html=1;strokeColor=none;fillColor=none;spacingLeft=4;spacingRight=4;whiteSpace=wrap;overflow=hidden;rotatable=0;points=[[0,0.5],[1,0.5]];portConstraint=eastwest;" parent="302e782255bbe1b2-87" vertex="1"><mxGeometry y="142" width="160" height="32" as="geometry"/></mxCell><mxCell id="302e782255bbe1b2-94" value="" style="edgeStyle=entityRelationEdgeStyle;html=1;endArrow=ERmandOne;startArrow=ERmandOne;exitX=1;exitY=0.5;entryX=0;entryY=0.5;" parent="1" source="70c1fabb3b7ea038-66" target="302e782255bbe1b2-89" edge="1"><mxGeometry x="610" y="141" width="100" height="100" as="geometry"><mxPoint x="614" y="141" as="sourcePoint"/><mxPoint x="350" y="409" as="targetPoint"/></mxGeometry></mxCell><mxCell id="70c1fabb3b7ea038-56" value="Organization" style="swimlane;html=1;fontStyle=0;childLayout=stackLayout;horizontal=1;startSize=26;fillColor=#e0e0e0;horizontalStack=0;resizeParent=1;resizeLast=0;collapsible=1;marginBottom=0;swimlaneFillColor=#ffffff;align=center;" parent="1" vertex="1"><mxGeometry x="340" y="86" width="160" height="188" as="geometry"/></mxCell><mxCell id="70c1fabb3b7ea038-57" value="name" style="text;html=1;strokeColor=none;fillColor=none;spacingLeft=4;spacingRight=4;whiteSpace=wrap;overflow=hidden;rotatable=0;points=[[0,0.5],[1,0.5]];portConstraint=eastwest;" parent="70c1fabb3b7ea038-56" vertex="1"><mxGeometry y="26" width="160" height="26" as="geometry"/></mxCell><mxCell id="70c1fabb3b7ea038-63" value="" style="edgeStyle=entityRelationEdgeStyle;html=1;endArrow=ERmandOne;startArrow=ERmandOne;entryX=0;entryY=0.5;exitX=1;exitY=0.5;" parent="1" source="70c1fabb3b7ea038-57" target="70c1fabb3b7ea038-53" edge="1"><mxGeometry width="100" height="100" relative="1" as="geometry"><mxPoint x="320" y="380" as="sourcePoint"/><mxPoint x="290" y="210" as="targetPoint"/></mxGeometry></mxCell><mxCell id="70c1fabb3b7ea038-71" value="" style="edgeStyle=elbowEdgeStyle;html=1;endArrow=ERmany;startArrow=ERmany;exitX=1;exitY=0.5;entryX=1;entryY=0.5;" parent="1" source="302e782255bbe1b2-88" target="11" edge="1"><mxGeometry width="100" height="100" relative="1" as="geometry"><mxPoint x="670" y="457" as="sourcePoint"/><mxPoint x="770" y="357" as="targetPoint"/><Array as="points"><mxPoint x="770" y="260"/></Array></mxGeometry></mxCell><mxCell id="70c1fabb3b7ea038-72" value="" style="edgeStyle=entityRelationEdgeStyle;html=1;endArrow=ERmany;startArrow=ERmany;exitX=0.944;exitY=-0.192;exitPerimeter=0;" parent="1" source="302e782255bbe1b2-66" edge="1"><mxGeometry width="100" height="100" relative="1" as="geometry"><mxPoint x="250" y="306" as="sourcePoint"/><mxPoint x="340" y="154" as="targetPoint"/></mxGeometry></mxCell><mxCell id="1559b20e4a066e21-53" value="Solutions" style="swimlane;html=1;fontStyle=0;childLayout=stackLayout;horizontal=1;startSize=26;fillColor=#e0e0e0;horizontalStack=0;resizeParent=1;resizeLast=0;collapsible=1;marginBottom=0;swimlaneFillColor=#ffffff;align=center;" vertex="1" parent="1"><mxGeometry x="630" y="369" width="160" height="121" as="geometry"><mxRectangle x="630" y="255" width="80" height="26" as="alternateBounds"/></mxGeometry></mxCell><mxCell id="1559b20e4a066e21-54" value="solution ID" style="text;html=1;strokeColor=none;fillColor=none;spacingLeft=4;spacingRight=4;whiteSpace=wrap;overflow=hidden;rotatable=0;points=[[0,0.5],[1,0.5]];portConstraint=eastwest;" vertex="1" parent="1559b20e4a066e21-53"><mxGeometry y="26" width="160" height="26" as="geometry"/></mxCell><mxCell id="1559b20e4a066e21-55" value="description" style="text;html=1;strokeColor=none;fillColor=none;spacingLeft=4;spacingRight=4;whiteSpace=wrap;overflow=hidden;rotatable=0;points=[[0,0.5],[1,0.5]];portConstraint=eastwest;" vertex="1" parent="1559b20e4a066e21-53"><mxGeometry y="52" width="160" height="26" as="geometry"/></mxCell><mxCell id="1559b20e4a066e21-59" value="&amp;nbsp;Big O" style="text;html=1;" vertex="1" parent="1559b20e4a066e21-53"><mxGeometry y="78" width="160" height="30" as="geometry"/></mxCell><mxCell id="1559b20e4a066e21-60" value="" style="edgeStyle=elbowEdgeStyle;html=1;endArrow=ERzeroToMany;startArrow=ERmandOne;exitX=1;exitY=0.5;entryX=1;entryY=0.5;" edge="1" parent="1" source="12" target="1559b20e4a066e21-55"><mxGeometry width="100" height="100" relative="1" as="geometry"><mxPoint x="660" y="608" as="sourcePoint"/><mxPoint x="760" y="508" as="targetPoint"/><Array as="points"><mxPoint x="820" y="290"/></Array></mxGeometry></mxCell></root></mxGraphModel>